apep/__init__.py
apep-0.0.1.dist-info/METADATA
apep-0.0.1.dist-info/WHEEL
apep-0.0.1.dist-info/top_level.txt
apep-0.0.1.dist-info/RECORD
